{"nodes": [{"weight": "2138", "cc": "3600", "dtype": "Front", "height": "1846", "enginepower": "281", "enginetype": "V", "group": "Chevrolet", "engineposition": "Front", "rpm": "6300", "hwymileage": "8.4", "width": "1991", "doors": "5", "fuel": "Gasoline", "ttype": "6-speed automatic ", "mileage": "12.7", "modeltrim": "LS FWD", "enginevalves": "4", "torguqnm": "361", "cylinders": "6", "name": "Traverse", "country": "USA", "wheelbase": "3020", "length": "5173", "torquerpm": "3400"}, {"weight": "1840", "cc": "3500", "dtype": "Front", "height": "1702", "enginepower": "285", "enginetype": "V", "group": "Ford", "engineposition": "Front", "rpm": "6500", "hwymileage": "7.2", "width": "2223", "doors": "5", "fuel": "Gasoline", "ttype": "6-speed automatic ", "mileage": "11.1", "modeltrim": "SE", "enginevalves": "4", "torguqnm": "343", "cylinders": "6", "name": "EDGE", "country": "USA", "wheelbase": "2824", "length": "4679", "torquerpm": "4000"}], "links": [{"source": 0, "target": 0, "weight": 3}, {"source": 1, "target": 1, "weight": 3}]}